pyground/__init__.py
pyground/ascii.py
pyground/aws.py
pyground/filesystem.py
pyground/goodreads.py
pyground/ini.py
pyground/json.py
pyground/jsonl.py
pyground/time.py
pyground/timestamps.py
pyground/types.py
pyground-0.0.7.dist-info/METADATA
pyground-0.0.7.dist-info/WHEEL
pyground-0.0.7.dist-info/top_level.txt
pyground-0.0.7.dist-info/RECORD
